keepkey_agent.py
setup.py
keepkey_agent.egg-info/PKG-INFO
keepkey_agent.egg-info/SOURCES.txt
keepkey_agent.egg-info/dependency_links.txt
keepkey_agent.egg-info/entry_points.txt
keepkey_agent.egg-info/requires.txt
keepkey_agent.egg-info/top_level.txt