Metadata-Version: 1.1
Name: keepkey-agent
Version: 0.9.0
Summary: Using KeepKey as hardware SSH/GPG agent
Home-page: http://github.com/romanz/trezor-agent
Author: Roman Zeyde
Author-email: roman.zeyde@gmail.com
License: UNKNOWN
Platform: POSIX
Classifier: Environment :: Console
Classifier: Development Status :: 4 - Beta
Classifier: Intended Audience :: Developers
Classifier: Intended Audience :: Information Technology
Classifier: Intended Audience :: System Administrators
Classifier: License :: OSI Approved :: GNU Lesser General Public License v3 (LGPLv3)
Classifier: Operating System :: POSIX
Classifier: Programming Language :: Python :: 2.7
Classifier: Programming Language :: Python :: 3.4
Classifier: Programming Language :: Python :: 3.5
Classifier: Topic :: Software Development :: Libraries :: Python Modules
Classifier: Topic :: System :: Networking
Classifier: Topic :: Communications
Classifier: Topic :: Security
Classifier: Topic :: Utilities
